LICENSE
MANIFEST.in
README.md
requirements.txt
setup.py
test-requirements.txt
r128gain/__init__.py
r128gain/__main__.py
r128gain/colored_logging.py
r128gain/opusgain.py
r128gain/tqdm_logging.py
r128gain.egg-info/PKG-INFO
r128gain.egg-info/SOURCES.txt
r128gain.egg-info/dependency_links.txt
r128gain.egg-info/entry_points.txt
r128gain.egg-info/requires.txt
r128gain.egg-info/top_level.txt