Metadata-Version: 2.1
Name: r128gain
Version: 1.0.1
Summary: Fast audio loudness scanner & tagger
Home-page: https://github.com/desbma/r128gain
Author: desbma
License: UNKNOWN
Download-URL: https://github.com/desbma/r128gain/archive/1.0.1.tar.gz
Keywords: audio,loudness,replaygain,replay,gain,r128,tag,opus,normalize,normalization,level
Platform: UNKNOWN
Classifier: Development Status :: 4 - Beta
Classifier: Environment :: Console
Classifier: Intended Audience :: End Users/Desktop
Classifier: Intended Audience :: Developers
Classifier: License :: OSI Approved :: GNU Lesser General Public License v2 or later (LGPLv2+)
Classifier: Operating System :: OS Independent
Classifier: Programming Language :: Python
Classifier: Programming Language :: Python :: 3
Classifier: Programming Language :: Python :: 3 :: Only
Classifier: Programming Language :: Python :: 3.5
Classifier: Programming Language :: Python :: 3.6
Classifier: Programming Language :: Python :: 3.7
Classifier: Programming Language :: Python :: 3.8
Classifier: Topic :: Multimedia :: Sound/Audio :: Analysis
Classifier: Topic :: Utilities
